{
  "$schema": "https://developer.microsoft.com/json-schemas/spfx-build/package-solution.schema.json",
  "solution": {
    "name": "ui-grid-client-side-solution",
    "id": "67d5b418-60ac-4ecf-a5dc-fa6819025bb8",
    "version": "1.0.0.0",
    "includeClientSideAssets": true,
    "skipFeatureDeployment": true,
    "isDomainIsolated": false,
    "developer": {
      "name": "",
      "websiteUrl": "",
      "privacyUrl": "",
      "termsOfUseUrl": "",
      "mpnId": "Undefined-1.15.2"
    },
    "metadata": {
      "shortDescription": {
        "default": "ui-grid description"
      },
      "longDescription": {
        "default": "ui-grid description"
      },
      "screenshotPaths": [],
      "videoUrl": "",
      "categories": []
    },
    "features": [
      {
        "title": "ui-grid Feature",
        "description": "The feature that activates elements of the ui-grid solution.",
        "id": "7357044b-59f4-4012-ba7d-610005679c2e",
        "version": "1.0.0.0"
      }
    ]
  },
  "paths": {
    "zippedPackage": "solution/ui-grid.sppkg"
  }
}
